click_man/__init__.py
click_man/core.py
click_man/man.py
click_man/shell.py
click_man-0.5.1.dist-info/licenses/LICENSE
click_man-0.5.1.dist-info/METADATA
click_man-0.5.1.dist-info/WHEEL
click_man-0.5.1.dist-info/entry_points.txt
click_man-0.5.1.dist-info/top_level.txt
click_man-0.5.1.dist-info/RECORD
