Metadata-Version: 2.4
Name: click-man
Version: 0.5.1
Summary: Generate man pages for click based CLI applications
Author-email: Timo Furrer <tuxtimo@gmail.com>
Maintainer-email: Timo Furrer <tuxtimo@gmail.com>, Stephen Finucane <stephen@that.guru>
License: MIT
Project-URL: Source, https://github.com/click-contrib/click-man
Classifier: Development Status :: 5 - Production/Stable
Classifier: Intended Audience :: Developers
Classifier: License :: OSI Approved :: MIT License
Classifier: Operating System :: OS Independent
Classifier: Programming Language :: Python :: 3
Classifier: Programming Language :: Python :: 3 :: Only
Classifier: Topic :: Documentation
Requires-Python: >=3.9
License-File: LICENSE
Requires-Dist: click
Dynamic: license-file
